mariadb_sqlbuilder/__init__.py
mariadb_sqlbuilder/connector.py
mariadb_sqlbuilder/exepetions.py
mariadb_sqlbuilder/builder/__init__.py
mariadb_sqlbuilder/builder/base_builder.py
mariadb_sqlbuilder/builder/delete_builder.py
mariadb_sqlbuilder/builder/dict_converter.py
mariadb_sqlbuilder/builder/exists_builder.py
mariadb_sqlbuilder/builder/insert_builder.py
mariadb_sqlbuilder/builder/join_builder.py
mariadb_sqlbuilder/builder/select_builder.py
mariadb_sqlbuilder/builder/update_builder.py
mariadb_sqlbuilder/builder/upsert_builder.py
mariadb_sqlbuilder/helpful/arithmetic.py
mariadb_sqlbuilder/helpful/conditions_saver.py
mariadb_sqlbuilder/helpful/connection_dummy.py
mariadb_sqlbuilder/helpful/filter_operator.py
mariadb_sqlbuilder/helpful/subquery_operator.py
mariadb_sqlbuilder/helpful/validator.py
mariadb_sqlbuilder/helpful/validator_dummy.py
mariadb_sqlbuilder/sqlscript/splitter.py
MariaDB_SQLBuilder-1.1.1.dist-info/LICENSE
MariaDB_SQLBuilder-1.1.1.dist-info/METADATA
MariaDB_SQLBuilder-1.1.1.dist-info/WHEEL
MariaDB_SQLBuilder-1.1.1.dist-info/top_level.txt
MariaDB_SQLBuilder-1.1.1.dist-info/RECORD
