Metadata-Version: 2.1
Name: MariaDB-SQLBuilder
Version: 1.1.1
Summary: MariaDB SQL Builder is a simple way to use Maria SQL. Use your own SQL or use the integrated Maria SQL Builder tool.
Home-page: https://github.com/princessmiku/MariaDB-SQLBuilder
Author: Miku
Author-email: 
License: LGPL 2.1
Keywords: database,mariadb,sql,builder,script builder,mariadb sql
Classifier: Programming Language :: Python :: 3.7
Classifier: Programming Language :: Python :: 3.8
Classifier: Programming Language :: Python :: 3.9
Classifier: Programming Language :: Python :: 3.10
Classifier: Programming Language :: Python :: 3.11
Requires-Python: >=3.7.0
License-File: LICENSE
Requires-Dist: mariadb >=1.1.6
